gakomail.py
gakomail-1.0.0.dist-info/METADATA
gakomail-1.0.0.dist-info/WHEEL
gakomail-1.0.0.dist-info/entry_points.txt
gakomail-1.0.0.dist-info/top_level.txt
gakomail-1.0.0.dist-info/RECORD
