Metadata-Version: 2.4
Name: gakomail
Version: 1.0.0
Summary: A Python script to send emails over SMTP SSL
Requires-Python: >=3.6
Requires-Dist: keyring
